CONTRIBUTORS.txt
LICENSE.txt
MANIFEST.in
README.rst
setup.py
django_admin_app_names_singleton.egg-info/PKG-INFO
django_admin_app_names_singleton.egg-info/SOURCES.txt
django_admin_app_names_singleton.egg-info/dependency_links.txt
django_admin_app_names_singleton.egg-info/top_level.txt
django_singleton_app_name/__init__.py
django_singleton_app_name/admin.py
django_singleton_app_name/models.py
django_singleton_app_name/templates/admin/change_form.html
django_singleton_app_name/templates/admin/change_list.html
django_singleton_app_name/templates/admin/index.html