Metadata-Version: 1.1
Name: django-admin-app-names-singleton
Version: 1.0
Summary: Django admin enhancer
Home-page: https://github.com/pylior/django-admin-app-names-singleton
Author: Lior Regev
Author-email: lioregev@gmail.com
License: MIT
Platform: UNKNOWN
Classifier: Environment :: Web Environment
Classifier: Framework :: Django
Classifier: Intended Audience :: Developers
Classifier: License :: OSI Approved :: MIT License
Classifier: Operating System :: OS Independent
Classifier: Programming Language :: Python
Classifier: Programming Language :: Python :: 2.6
Classifier: Programming Language :: Python :: 2.7
Classifier: Topic :: Internet :: WWW/HTTP
Classifier: Topic :: Internet :: WWW/HTTP :: Dynamic Content
